README.txt
setup.cfg
setup.py
docs/HISTORY.txt
neteasy/__init__.py
neteasy.plone.subnavbar.egg-info/PKG-INFO
neteasy.plone.subnavbar.egg-info/SOURCES.txt
neteasy.plone.subnavbar.egg-info/dependency_links.txt
neteasy.plone.subnavbar.egg-info/entry_points.txt
neteasy.plone.subnavbar.egg-info/namespace_packages.txt
neteasy.plone.subnavbar.egg-info/not-zip-safe
neteasy.plone.subnavbar.egg-info/requires.txt
neteasy.plone.subnavbar.egg-info/top_level.txt
neteasy/plone/__init__.py
neteasy/plone/subnavbar/__init__.py
neteasy/plone/subnavbar/configure.zcml
neteasy/plone/subnavbar/interfaces.py
neteasy/plone/subnavbar/navbar_contents.py
neteasy/plone/subnavbar/profiles.zcml
neteasy/plone/subnavbar/tests.py
neteasy/plone/subnavbar/version.txt
neteasy/plone/subnavbar/browser/__init__.py
neteasy/plone/subnavbar/browser/configure.zcml
neteasy/plone/subnavbar/browser/subnavbar.pt
neteasy/plone/subnavbar/browser/subnavbar.py
neteasy/plone/subnavbar/profiles/default/browserlayer.xml
neteasy/plone/subnavbar/profiles/default/cssregistry.xml
neteasy/plone/subnavbar/profiles/default/skins.xml
neteasy/plone/subnavbar/skins/neteasy.plone.subnavbar/subnavbar.css.dtml