Metadata-Version: 1.0
Name: neteasy.plone.subnavbar
Version: 1.0.0-release
Summary: Second level navbar for Plone sites
Home-page: http://neteasyinc.com
Author: Jim Nelson
Author-email: jim.nelson@neteasyinc.com
License: GPL
Keywords: Plone
Platform: UNKNOWN
Classifier: Programming Language :: Python
Classifier: Topic :: Software Development :: Libraries :: Python Modules
